anngtf/__init__.py
anngtf/_parse/_add_gtf_annotations_to_adata.py
anngtf/_parse/_load_gtf_csv.py
anngtf/_parse/_parse_gtf_to_csv.py
anngtf-0.0.11.dist-info/LICENSE
anngtf-0.0.11.dist-info/METADATA
anngtf-0.0.11.dist-info/WHEEL
anngtf-0.0.11.dist-info/top_level.txt
anngtf-0.0.11.dist-info/RECORD
